sqlite_utils/__init__.py
sqlite_utils/__main__.py
sqlite_utils/cli.py
sqlite_utils/db.py
sqlite_utils/hookspecs.py
sqlite_utils/plugins.py
sqlite_utils/py.typed
sqlite_utils/recipes.py
sqlite_utils/utils.py
sqlite_utils-3.37.dist-info/LICENSE
sqlite_utils-3.37.dist-info/METADATA
sqlite_utils-3.37.dist-info/WHEEL
sqlite_utils-3.37.dist-info/entry_points.txt
sqlite_utils-3.37.dist-info/top_level.txt
sqlite_utils-3.37.dist-info/RECORD
