Metadata-Version: 2.1
Name: sqlite-utils
Version: 3.37
Summary: CLI tool and Python library for manipulating SQLite databases
Home-page: https://github.com/simonw/sqlite-utils
Author: Simon Willison
License: Apache License, Version 2.0
Project-URL: Documentation, https://sqlite-utils.datasette.io/en/stable/
Project-URL: Changelog, https://sqlite-utils.datasette.io/en/stable/changelog.html
Project-URL: Source code, https://github.com/simonw/sqlite-utils
Project-URL: Issues, https://github.com/simonw/sqlite-utils/issues
Project-URL: CI, https://github.com/simonw/sqlite-utils/actions
Classifier: Development Status :: 5 - Production/Stable
Classifier: Intended Audience :: Developers
Classifier: Intended Audience :: Science/Research
Classifier: Intended Audience :: End Users/Desktop
Classifier: Topic :: Database
Classifier: License :: OSI Approved :: Apache Software License
Classifier: Programming Language :: Python :: 3.8
Classifier: Programming Language :: Python :: 3.9
Classifier: Programming Language :: Python :: 3.10
Classifier: Programming Language :: Python :: 3.11
Classifier: Programming Language :: Python :: 3.12
Classifier: Programming Language :: Python :: 3.13
Requires-Python: >=3.8
License-File: LICENSE
Requires-Dist: sqlite-fts4
Requires-Dist: click
Requires-Dist: click-default-group>=1.2.3
Requires-Dist: tabulate
Requires-Dist: python-dateutil
Requires-Dist: pluggy
Provides-Extra: test
Requires-Dist: pytest; extra == "test"
Requires-Dist: black>=24.1.1; extra == "test"
Requires-Dist: hypothesis; extra == "test"
Requires-Dist: cogapp; extra == "test"
Provides-Extra: docs
Requires-Dist: furo; extra == "docs"
Requires-Dist: sphinx-autobuild; extra == "docs"
Requires-Dist: codespell; extra == "docs"
Requires-Dist: sphinx-copybutton; extra == "docs"
Requires-Dist: beanbag-docutils>=2.0; extra == "docs"
Requires-Dist: pygments-csv-lexer; extra == "docs"
Provides-Extra: mypy
Requires-Dist: mypy; extra == "mypy"
Requires-Dist: types-click; extra == "mypy"
Requires-Dist: types-tabulate; extra == "mypy"
Requires-Dist: types-python-dateutil; extra == "mypy"
Requires-Dist: types-pluggy; extra == "mypy"
Requires-Dist: data-science-types; extra == "mypy"
Provides-Extra: flake8
Requires-Dist: flake8; extra == "flake8"
Provides-Extra: tui
Requires-Dist: trogon; extra == "tui"
